phylib/__init__.py
phylib/conftest.py
phylib/electrode/__init__.py
phylib/electrode/mea.py
phylib/electrode/probes/1x32_buzsaki.prb
phylib/electrode/tests/__init__.py
phylib/electrode/tests/test_mea.py
phylib/io/__init__.py
phylib/io/alf.py
phylib/io/array.py
phylib/io/datasets.py
phylib/io/merge.py
phylib/io/mock.py
phylib/io/model.py
phylib/io/traces.py
phylib/io/tests/__init__.py
phylib/io/tests/conftest.py
phylib/io/tests/test_alf.py
phylib/io/tests/test_array.py
phylib/io/tests/test_datasets.py
phylib/io/tests/test_merge.py
phylib/io/tests/test_mock.py
phylib/io/tests/test_model.py
phylib/io/tests/test_traces.py
phylib/stats/__init__.py
phylib/stats/ccg.py
phylib/stats/clusters.py
phylib/stats/tests/__init__.py
phylib/stats/tests/test_ccg.py
phylib/stats/tests/test_clusters.py
phylib/utils/__init__.py
phylib/utils/_misc.py
phylib/utils/_types.py
phylib/utils/event.py
phylib/utils/geometry.py
phylib/utils/testing.py
phylib/utils/tests/__init__.py
phylib/utils/tests/test_event.py
phylib/utils/tests/test_geometry.py
phylib/utils/tests/test_misc.py
phylib/utils/tests/test_testing.py
phylib/utils/tests/test_types.py
phylib-2.7.0.dist-info/LICENSE.md
phylib-2.7.0.dist-info/METADATA
phylib-2.7.0.dist-info/WHEEL
phylib-2.7.0.dist-info/top_level.txt
phylib-2.7.0.dist-info/RECORD
