Metadata-Version: 2.1
Name: phylib
Version: 2.7.0
Summary: Ephys data analysis for thousands of channels
Home-page: https://github.com/cortex-lab/phylib
Author: Cyrille Rossant
Author-email: cyrille.rossant@gmail.com
License: BSD
Keywords: phy,data analysis,electrophysiology,neuroscience
Classifier: Development Status :: 4 - Beta
Classifier: Intended Audience :: Developers
Classifier: License :: OSI Approved :: BSD License
Classifier: Natural Language :: English
Classifier: Framework :: IPython
Classifier: Programming Language :: Python :: 3
Classifier: Programming Language :: Python :: 3.7
License-File: LICENSE.md
Requires-Dist: numpy
Requires-Dist: scipy
Requires-Dist: dask
Requires-Dist: requests
Requires-Dist: responses
Requires-Dist: tqdm
Requires-Dist: toolz
Requires-Dist: joblib
Requires-Dist: mtscomp
